layermesh/__init__.py
layermesh/geometry.py
layermesh/mesh.py
layermesh/quadtree.py
layermesh-0.4.1.dist-info/LICENSE
layermesh-0.4.1.dist-info/METADATA
layermesh-0.4.1.dist-info/WHEEL
layermesh-0.4.1.dist-info/top_level.txt
layermesh-0.4.1.dist-info/RECORD
