Metadata-Version: 2.1
Name: layermesh
Version: 0.4.1
Summary: Library for layered computational meshes
Author-email: Adrian Croucher <a.croucher@auckland.ac.nz>
License: GNU LESSER GENERAL PUBLIC LICENSE
Project-URL: repository, http://github.com/acroucher/layermesh
Classifier: Programming Language :: Python :: 2
Classifier: Programming Language :: Python :: 3
Classifier: License :: OSI Approved :: GNU Lesser General Public License v3 (LGPLv3)
Classifier: Operating System :: OS Independent
Requires-Python: >=2.7
License-File: LICENSE
Requires-Dist: numpy
Requires-Dist: scipy
Requires-Dist: h5py
Requires-Dist: meshio
Requires-Dist: matplotlib
